OrcidXtract/__init__.py
OrcidXtract/constants.py
OrcidXtract/exceptions.py
OrcidXtract/main.py
OrcidXtract/orcid_extractor.py
OrcidXtract/report_generator.py
OrcidXtract/restfull.py
OrcidXtract/test.py
OrcidXtract/utils.py
OrcidXtract-0.0.6.dist-info/METADATA
OrcidXtract-0.0.6.dist-info/WHEEL
OrcidXtract-0.0.6.dist-info/entry_points.txt
OrcidXtract-0.0.6.dist-info/top_level.txt
OrcidXtract-0.0.6.dist-info/RECORD
