Metadata-Version: 2.2
Name: OrcidXtract
Version: 0.0.6
Summary: This Python library extracts ORCID information from a file containing ORCID IDs and generates reports in various formats (TXT, PDF, JSON, CSV, Excel).
Home-page: https://github.com/SafialIslam302/ORCID-Information
Author: Safial Islam Ayon
Author-email: safialislam302@gmail.com
Classifier: Programming Language :: Python :: 3
Classifier: License :: OSI Approved :: MIT License
Classifier: Operating System :: OS Independent
Requires-Python: >=3.6
Requires-Dist: requests
Requires-Dist: pandas
Requires-Dist: reportlab~=4.3.1
Requires-Dist: openpyxl
Requires-Dist: pytest
Requires-Dist: coverage
Requires-Dist: typing_extensions
Requires-Dist: setuptools
Dynamic: author
Dynamic: author-email
Dynamic: classifier
Dynamic: description
Dynamic: description-content-type
Dynamic: home-page
Dynamic: requires-dist
Dynamic: requires-python
Dynamic: summary
